Aphid/__init__.py
Aphid/objects.py
Aphid/recursion_tools.py
Aphid/tests.py
Aphid-0.1.1.dist-info/METADATA
Aphid-0.1.1.dist-info/WHEEL
Aphid-0.1.1.dist-info/top_level.txt
Aphid-0.1.1.dist-info/RECORD
