Metadata-Version: 2.1
Name: Aphid
Version: 0.1.1
Summary: A toolkit for working with nested data types
Home-page: https://github.com/robertkearns/Aphid
Author: Robert Kearns
Author-email: rxk0914@hotmail.com
License: UNKNOWN
Platform: UNKNOWN
